very_cool_functions/__init__.py
very_cool_functions-0.1.2.dist-info/WHEEL
very_cool_functions-0.1.2.dist-info/METADATA
very_cool_functions-0.1.2.dist-info/RECORD
