Metadata-Version: 2.1
Name: very-cool-functions
Version: 0.1.2
Summary: various helpful and fun functions
Author: Magic Man
Author-email: zmartine0031@mymail.lausd.net
Requires-Python: >=3.8,<4.0
Classifier: Programming Language :: Python :: 3
Classifier: Programming Language :: Python :: 3.10
Classifier: Programming Language :: Python :: 3.8
Classifier: Programming Language :: Python :: 3.9
